packyak_aws_cdk/__init__.py
packyak_aws_cdk/py.typed
packyak_aws_cdk/_jsii/__init__.py
packyak_aws_cdk/_jsii/aws-cdk@0.4.37.jsii.tgz
packyak_aws_cdk-0.4.37.data/scripts/packyak
packyak_aws_cdk-0.4.37.dist-info/LICENSE
packyak_aws_cdk-0.4.37.dist-info/METADATA
packyak_aws_cdk-0.4.37.dist-info/WHEEL
packyak_aws_cdk-0.4.37.dist-info/top_level.txt
packyak_aws_cdk-0.4.37.dist-info/RECORD
