Metadata-Version: 2.1
Name: packyak-aws-cdk
Version: 0.4.37
Summary: AWS CDK Constructs for the PackYak Lakehouse Platform
Home-page: https://github.com/sam-goodwin/packyak
Author: Sam Goodwin
License: Apache-2.0
Project-URL: Source, https://github.com/sam-goodwin/packyak
Classifier: Intended Audience :: Developers
Classifier: Operating System :: OS Independent
Classifier: Programming Language :: JavaScript
Classifier: Programming Language :: Python :: 3 :: Only
Classifier: Programming Language :: Python :: 3.8
Classifier: Programming Language :: Python :: 3.9
Classifier: Programming Language :: Python :: 3.10
Classifier: Programming Language :: Python :: 3.11
Classifier: Typing :: Typed
Classifier: Development Status :: 4 - Beta
Classifier: License :: OSI Approved
Classifier: Framework :: AWS CDK
Classifier: Framework :: AWS CDK :: 1
Requires-Python: ~=3.8
License-File: LICENSE
Requires-Dist: aws-cdk-lib ==2.134.0
Requires-Dist: aws-cdk.aws-glue-alpha ==2.134.0.a0
Requires-Dist: aws-cdk.aws-lambda-python-alpha ==2.134.0.a0
Requires-Dist: aws-cdk.aws-sagemaker-alpha ==2.134.0.a0
Requires-Dist: constructs <11.0.0,>=10.3.0
Requires-Dist: jsii <2.0.0,>=1.94.0
Requires-Dist: publication >=0.0.3
Requires-Dist: typeguard ~=2.13.3
